backgammon/__init__.py
backgammon/example.py
backgammon/frontend/build/asset-manifest.json
backgammon/frontend/build/bootstrap.min.css
backgammon/frontend/build/index.html
backgammon/frontend/build/static/css/main.5ea8fc2e.css
backgammon/frontend/build/static/css/main.5ea8fc2e.css.map
backgammon/frontend/build/static/js/main.3aadc75f.js
backgammon/frontend/build/static/js/main.3aadc75f.js.LICENSE.txt
backgammon/frontend/build/static/js/main.3aadc75f.js.map
backgammon/frontend/build/static/js/main.438f4da2.js
backgammon/frontend/build/static/js/main.438f4da2.js.LICENSE.txt
backgammon/frontend/build/static/js/main.438f4da2.js.map
backgammon/frontend/build/static/js/main.a89c350a.js
backgammon/frontend/build/static/js/main.a89c350a.js.LICENSE.txt
backgammon/frontend/build/static/js/main.a89c350a.js.map
backgammon/frontend/build/static/js/main.f43df712.js
backgammon/frontend/build/static/js/main.f43df712.js.LICENSE.txt
backgammon/frontend/build/static/js/main.f43df712.js.map
my_component/__init__.py
my_component/example.py
slider_with_buttons/__init__.py
slider_with_buttons/example.py
slider_with_buttons/frontend/build/asset-manifest.json
slider_with_buttons/frontend/build/bootstrap.min.css
slider_with_buttons/frontend/build/index.html
slider_with_buttons/frontend/build/static/js/main.3ebcf6e0.js
slider_with_buttons/frontend/build/static/js/main.3ebcf6e0.js.LICENSE.txt
slider_with_buttons/frontend/build/static/js/main.3ebcf6e0.js.map
slider_with_buttons/frontend/build/static/js/main.45e54f85.js
slider_with_buttons/frontend/build/static/js/main.45e54f85.js.LICENSE.txt
slider_with_buttons/frontend/build/static/js/main.45e54f85.js.map
slider_with_buttons/frontend/build/static/js/main.9554f9d0.js
slider_with_buttons/frontend/build/static/js/main.9554f9d0.js.LICENSE.txt
slider_with_buttons/frontend/build/static/js/main.9554f9d0.js.map
slider_with_buttons/frontend/build/static/js/main.d9212a54.js
slider_with_buttons/frontend/build/static/js/main.d9212a54.js.LICENSE.txt
slider_with_buttons-0.0.6.dist-info/LICENSE
slider_with_buttons-0.0.6.dist-info/METADATA
slider_with_buttons-0.0.6.dist-info/WHEEL
slider_with_buttons-0.0.6.dist-info/top_level.txt
slider_with_buttons-0.0.6.dist-info/RECORD
